damatu/__init__.py
damatu-0.1.dist-info/METADATA
damatu-0.1.dist-info/RECORD
damatu-0.1.dist-info/WHEEL
damatu-0.1.dist-info/top_level.txt
