Metadata-Version: 2.1
Name: damatu
Version: 0.1
Summary: damatu python sdk
Home-page: https://github.com/youngershen/damatu
Author: Younger Shen
Author-email: younger.shen@hotmail.com
License: MIT
Keywords: damatu,captcha
Platform: UNKNOWN
Classifier: Development Status :: 3 - Alpha
Classifier: Intended Audience :: Developers
Classifier: License :: OSI Approved :: MIT License
Classifier: Programming Language :: Python :: 3.6
Classifier: Programming Language :: Python :: 2.7
